opendelta/__init__.py
opendelta/auto_delta.py
opendelta/basemodel.py
opendelta/delta_configs.py
opendelta/delta_models/__init__.py
opendelta/delta_models/adapter.py
opendelta/delta_models/bitfit.py
opendelta/delta_models/compacter.py
opendelta/delta_models/lora.py
opendelta/delta_models/low_rank_adapter.py
opendelta/delta_models/parallel_adapter.py
opendelta/delta_models/prefix.py
opendelta/delta_models/soft_prompt.py
opendelta/delta_models/layers/__init__.py
opendelta/delta_models/layers/activations.py
opendelta/delta_models/layers/hypercomplex_linear.py
opendelta/delta_models/layers/init.py
opendelta/delta_models/layers/low_rank_linear.py
opendelta/utils/__init__.py
opendelta/utils/backend.py
opendelta/utils/cuda.py
opendelta/utils/data_parallel.py
opendelta/utils/decorate.py
opendelta/utils/delta_center.py
opendelta/utils/delta_hub.py
opendelta/utils/file_utils.py
opendelta/utils/inspect.py
opendelta/utils/logging.py
opendelta/utils/model_md5.py
opendelta/utils/name_based_addressing.py
opendelta/utils/saving_loading_utils.py
opendelta/utils/signature.py
opendelta/utils/structure_mapping.py
opendelta/utils/visualization.py
opendelta/utils/common_structures/__init__.py
opendelta/utils/common_structures/bert.py
opendelta/utils/common_structures/debertav2.py
opendelta/utils/common_structures/gpt2.py
opendelta/utils/common_structures/opt.py
opendelta/utils/common_structures/roberta.py
opendelta/utils/common_structures/t5.py
opendelta/utils/interactive/__init__.py
opendelta/utils/interactive/web.py
opendelta/utils/interactive/templates/index.html
opendelta-0.3.2.dist-info/LICENSE
opendelta-0.3.2.dist-info/METADATA
opendelta-0.3.2.dist-info/WHEEL
opendelta-0.3.2.dist-info/top_level.txt
opendelta-0.3.2.dist-info/RECORD
