Metadata-Version: 2.1
Name: opendelta
Version: 0.3.2
Summary: An open source framework for delta learning (parameter efficient learning).
Home-page: https://github.com/thunlp/OpenDelta
Author: 
Author-email: shengdinghu@gmail.com
License: Apache
Keywords: PLM,Parameter-efficient-Learning,AI,NLP
Classifier: Programming Language :: Python :: 3
Classifier: Programming Language :: Python :: 3.8
Classifier: Programming Language :: Python :: 3.9
Classifier: Intended Audience :: Developers
Classifier: Intended Audience :: Education
Classifier: Intended Audience :: Science/Research
Classifier: License :: OSI Approved :: Apache Software License
Classifier: Operating System :: OS Independent
Requires-Python: >=3.6.0
License-File: LICENSE
Requires-Dist: torch (>=1.8.0)
Requires-Dist: transformers (>=4.10.0)
Requires-Dist: datasets (>=1.17.0)
Requires-Dist: sentencepiece (>=0.1.96)
Requires-Dist: tqdm (>=4.62.2)
Requires-Dist: decorator
Requires-Dist: rich
Requires-Dist: web.py
Requires-Dist: gitpython
Requires-Dist: scipy
Requires-Dist: sklearn
Requires-Dist: delta-center-client (==0.0.4)
